wink_sdk_analytics/__init__.py
wink_sdk_analytics/api_client.py
wink_sdk_analytics/api_response.py
wink_sdk_analytics/configuration.py
wink_sdk_analytics/exceptions.py
wink_sdk_analytics/py.typed
wink_sdk_analytics/rest.py
wink_sdk_analytics/api/__init__.py
wink_sdk_analytics/api/affiliate_api.py
wink_sdk_analytics/api/analytics_api.py
wink_sdk_analytics/api/leaderboard_api.py
wink_sdk_analytics/models/__init__.py
wink_sdk_analytics/models/aggregate_descriptor_authenticated_entity.py
wink_sdk_analytics/models/aggregate_descriptor_non_authenticated_entity.py
wink_sdk_analytics/models/aggregate_shares_projection_authenticated_entity.py
wink_sdk_analytics/models/auto_base_unit_steps_non_authenticated_entity.py
wink_sdk_analytics/models/axis_line_non_authenticated_entity.py
wink_sdk_analytics/models/axis_ticks_non_authenticated_entity.py
wink_sdk_analytics/models/booking_leaderboard_entry_non_authenticated_entity.py
wink_sdk_analytics/models/border_non_authenticated_entity.py
wink_sdk_analytics/models/category_axis_crosshair_non_authenticated_entity.py
wink_sdk_analytics/models/category_axis_crosshair_tooltip_non_authenticated_entity.py
wink_sdk_analytics/models/category_axis_notes_icon_non_authenticated_entity.py
wink_sdk_analytics/models/category_axis_notes_label_non_authenticated_entity.py
wink_sdk_analytics/models/category_axis_notes_non_authenticated_entity.py
wink_sdk_analytics/models/category_axis_select_non_authenticated_entity.py
wink_sdk_analytics/models/category_axis_title_non_authenticated_entity.py
wink_sdk_analytics/models/chart_authenticated_entity.py
wink_sdk_analytics/models/chart_category_axis_authenticated_entity.py
wink_sdk_analytics/models/chart_category_axis_labels_non_authenticated_entity.py
wink_sdk_analytics/models/chart_category_axis_major_grid_lines_non_authenticated_entity.py
wink_sdk_analytics/models/chart_category_axis_non_authenticated_entity.py
wink_sdk_analytics/models/chart_details_authenticated_entity.py
wink_sdk_analytics-0.0.57.dist-info/licenses/LICENSE
wink_sdk_analytics-0.0.57.dist-info/METADATA
wink_sdk_analytics-0.0.57.dist-info/WHEEL
wink_sdk_analytics-0.0.57.dist-info/top_level.txt
wink_sdk_analytics-0.0.57.dist-info/RECORD
